{
    "1": {
        "current_set": 1,
        "sides_changed": 0,
        "Action_FB_init_top": "Backhand",
        "Action_wl_init_top": "Winner",
        "shot": "Placement",
        "current_rally_top_init_score": 1,
        "current_rally_bottom_init_score": 0,
        "current_set_top_init_score": 1,
        "current_set_bottom_init_score": 0,
        "location_contact_shuttle": [
            700,
            808,
            5
        ],
        "location_end_shuttle": [
            680,
            1026,
            0
        ],
        "location_Init_start_top": -1,
        "location_Init_start_bottom": -1,
        "location_Init_end_top": -1,
        "location_Init_end_bottom": -1
    },
    "2": {
        "current_set": 1,
        "sides_changed": 0,
        "Action_FB_init_bottom": "Backhand",
        "Action_wl_init_bottom": "Winner",
        "shot": "Placement",
        "current_rally_top_init_score": 0,
        "current_rally_bottom_init_score": 1,
        "current_set_top_init_score": 1,
        "current_set_bottom_init_score": 1,
        "location_contact_shuttle": [
            392,
            1146,
            5
        ],
        "location_end_shuttle": [
            648,
            791,
            0
        ],
        "location_Init_start_top": -1,
        "location_Init_start_bottom": -1,
        "location_Init_end_top": -1,
        "location_Init_end_bottom": -1
    },
    "3": {
        "current_set": 1,
        "sides_changed": 0,
        "Action_FB_init_bottom": "Forehand",
        "Action_wl_init_bottom": "Mistake",
        "shot": "Placement",
        "current_rally_top_init_score": 1,
        "current_rally_bottom_init_score": 0,
        "current_set_top_init_score": 2,
        "current_set_bottom_init_score": 1,
        "location_contact_shuttle": [
            656,
            1373,
            5
        ],
        "location_end_shuttle": [
            818,
            340,
            0
        ],
        "location_Init_start_top": [
            [
                273,
                363
            ],
            [
                273,
                363
            ]
        ],
        "location_Init_start_bottom": [
            [
                515,
                1094
            ],
            [
                518,
                1101
            ]
        ],
        "location_Init_end_top": [
            [
                305,
                339
            ],
            [
                305,
                339
            ]
        ],
        "location_Init_end_bottom": -1
    },
    "4": {
        "current_set": 1,
        "sides_changed": 0,
        "Action_FB_init_top": "Forehand",
        "Action_wl_init_top": "Mistake",
        "shot": "Placement",
        "current_rally_top_init_score": 0,
        "current_rally_bottom_init_score": 1,
        "current_set_top_init_score": 2,
        "current_set_bottom_init_score": 2,
        "location_contact_shuttle": [
            375,
            696,
            5
        ],
        "location_end_shuttle": [
            186,
            1006,
            0
        ],
        "location_Init_start_top": -1,
        "location_Init_start_bottom": -1,
        "location_Init_end_top": -1,
        "location_Init_end_bottom": -1
    },
    "5": {
        "current_set": 1,
        "sides_changed": 0,
        "Action_FB_init_bottom": "Forehand",
        "Action_wl_init_bottom": "Winner",
        "shot": "Placement",
        "current_rally_top_init_score": 0,
        "current_rally_bottom_init_score": 1,
        "current_set_top_init_score": 2,
        "current_set_bottom_init_score": 3,
        "location_contact_shuttle": [
            525,
            1336,
            5
        ],
        "location_end_shuttle": [
            319,
            339,
            0
        ],
        "location_Init_start_top": -1,
        "location_Init_start_bottom": -1,
        "location_Init_end_top": -1,
        "location_Init_end_bottom": -1
    },
    "6": {
        "current_set": 1,
        "sides_changed": 0,
        "Action_FB_init_top": "Backhand",
        "Action_wl_init_top": "Mistake",
        "shot": "Net Shot",
        "current_rally_top_init_score": 0,
        "current_rally_bottom_init_score": 1,
        "current_set_top_init_score": 2,
        "current_set_bottom_init_score": 4,
        "location_contact_shuttle": [
            715,
            725,
            5
        ],
        "location_end_shuttle": [
            723,
            316,
            0
        ],
        "location_Init_start_top": -1,
        "location_Init_start_bottom": -1,
        "location_Init_end_top": -1,
        "location_Init_end_bottom": -1
    },
    "7": {
        "current_set": 1,
        "sides_changed": 0,
        "Action_FB_init_top": "Forehand",
        "Action_wl_init_top": "Winner",
        "shot": "Placement",
        "current_rally_top_init_score": 1,
        "current_rally_bottom_init_score": 0,
        "current_set_top_init_score": 3,
        "current_set_bottom_init_score": 4,
        "location_contact_shuttle": [
            700,
            438,
            5
        ],
        "location_end_shuttle": [
            726,
            1125,
            0
        ],
        "location_Init_start_top": [
            [
                524,
                596
            ],
            [
                493,
                596
            ]
        ],
        "location_Init_start_bottom": -1,
        "location_Init_end_top": -1,
        "location_Init_end_bottom": -1
    },
    "8": {
        "current_set": 1,
        "sides_changed": 0,
        "Action_FB_init_bottom": "Forehand",
        "Action_wl_init_bottom": "Mistake",
        "shot": "Net Shot",
        "current_rally_top_init_score": 1,
        "current_rally_bottom_init_score": 0,
        "current_set_top_init_score": 4,
        "current_set_bottom_init_score": 4,
        "location_contact_shuttle": [
            648,
            1182,
            5
        ],
        "location_end_shuttle": [
            734,
            228,
            0
        ],
        "location_Init_start_top": -1,
        "location_Init_start_bottom": -1,
        "location_Init_end_top": -1,
        "location_Init_end_bottom": -1
    },
    "9": {
        "current_set": 1,
        "sides_changed": 0,
        "Action_FB_init_bottom": "Forehand",
        "Action_wl_init_bottom": "Winner",
        "shot": "Placement",
        "current_rally_top_init_score": 0,
        "current_rally_bottom_init_score": 1,
        "current_set_top_init_score": 4,
        "current_set_bottom_init_score": 5,
        "location_contact_shuttle": [
            363,
            1374,
            5
        ],
        "location_end_shuttle": [
            268,
            658,
            0
        ],
        "location_Init_start_top": -1,
        "location_Init_start_bottom": [
            [
                244,
                1463
            ],
            [
                306,
                1482
            ]
        ],
        "location_Init_end_top": -1,
        "location_Init_end_bottom": -1
    },
    "10": {
        "current_set": 1,
        "sides_changed": 0,
        "Action_FB_init_bottom": "Forehand",
        "Action_wl_init_bottom": "Mistake",
        "shot": "Placement",
        "current_rally_top_init_score": 1,
        "current_rally_bottom_init_score": 0,
        "current_set_top_init_score": 5,
        "current_set_bottom_init_score": 5,
        "location_contact_shuttle": [
            458,
            1385,
            5
        ],
        "location_end_shuttle": [
            682,
            248,
            0
        ],
        "location_Init_start_top": -1,
        "location_Init_start_bottom": -1,
        "location_Init_end_top": -1,
        "location_Init_end_bottom": -1
    },
    "11": {
        "current_set": 1,
        "sides_changed": 0,
        "Action_FB_init_bottom": "Backhand",
        "Action_wl_init_bottom": "Mistake",
        "shot": "Placement",
        "current_rally_top_init_score": 1,
        "current_rally_bottom_init_score": 0,
        "current_set_top_init_score": 6,
        "current_set_bottom_init_score": 5,
        "location_contact_shuttle": [
            477,
            1441,
            5
        ],
        "location_end_shuttle": [
            869,
            562,
            0
        ],
        "location_Init_start_top": -1,
        "location_Init_start_bottom": -1,
        "location_Init_end_top": -1,
        "location_Init_end_bottom": -1
    },
    "12": {
        "current_set": 1,
        "sides_changed": 0,
        "Action_FB_init_top": "Forehand",
        "Action_wl_init_top": "Mistake",
        "shot": "Net Shot",
        "current_rally_top_init_score": 0,
        "current_rally_bottom_init_score": 1,
        "current_set_top_init_score": 6,
        "current_set_bottom_init_score": 6,
        "location_contact_shuttle": [
            352,
            678,
            5
        ],
        "location_end_shuttle": [
            607,
            297,
            0
        ],
        "location_Init_start_top": -1,
        "location_Init_start_bottom": -1,
        "location_Init_end_top": -1,
        "location_Init_end_bottom": -1
    },
    "13": {
        "current_set": 1,
        "sides_changed": 0,
        "Action_FB_init_bottom": "Backhand",
        "Action_wl_init_bottom": "Mistake",
        "shot": "Net Shot",
        "current_rally_top_init_score": 1,
        "current_rally_bottom_init_score": 0,
        "current_set_top_init_score": 7,
        "current_set_bottom_init_score": 6,
        "location_contact_shuttle": [
            288,
            1179,
            5
        ],
        "location_end_shuttle": [
            609,
            410,
            0
        ],
        "location_Init_start_top": -1,
        "location_Init_start_bottom": -1,
        "location_Init_end_top": -1,
        "location_Init_end_bottom": -1
    },
    "14": {
        "current_set": 1,
        "sides_changed": 0,
        "Action_FB_init_bottom": "Forehand",
        "Action_wl_init_bottom": "Mistake",
        "shot": "Net Shot",
        "current_rally_top_init_score": 1,
        "current_rally_bottom_init_score": 0,
        "current_set_top_init_score": 8,
        "current_set_bottom_init_score": 6,
        "location_contact_shuttle": [
            298,
            1500,
            5
        ],
        "location_end_shuttle": [
            652,
            328,
            0
        ],
        "location_Init_start_top": -1,
        "location_Init_start_bottom": -1,
        "location_Init_end_top": -1,
        "location_Init_end_bottom": -1
    },
    "15": {
        "current_set": 1,
        "sides_changed": 0,
        "Action_FB_init_top": "Backhand",
        "Action_wl_init_top": "Mistake",
        "shot": "Net Shot",
        "current_rally_top_init_score": 0,
        "current_rally_bottom_init_score": 1,
        "current_set_top_init_score": 8,
        "current_set_bottom_init_score": 7,
        "location_contact_shuttle": [
            680,
            660,
            5
        ],
        "location_end_shuttle": [
            868,
            387,
            0
        ],
        "location_Init_start_top": -1,
        "location_Init_start_bottom": -1,
        "location_Init_end_top": -1,
        "location_Init_end_bottom": -1
    },
    "16": {
        "current_set": 1,
        "sides_changed": 0,
        "Action_FB_init_top": "Forehand",
        "Action_wl_init_top": "Mistake",
        "shot": "Net Shot",
        "current_rally_top_init_score": 0,
        "current_rally_bottom_init_score": 1,
        "current_set_top_init_score": 8,
        "current_set_bottom_init_score": 8,
        "location_contact_shuttle": [
            680,
            498,
            5
        ],
        "location_end_shuttle": [
            407,
            481,
            0
        ],
        "location_Init_start_top": -1,
        "location_Init_start_bottom": -1,
        "location_Init_end_top": -1,
        "location_Init_end_bottom": -1
    },
    "17": {
        "current_set": 1,
        "sides_changed": 0,
        "Action_FB_init_top": "Forehand",
        "Action_wl_init_top": "Mistake",
        "shot": "Placement",
        "current_rally_top_init_score": 0,
        "current_rally_bottom_init_score": 1,
        "current_set_top_init_score": 8,
        "current_set_bottom_init_score": 9,
        "location_contact_shuttle": [
            654,
            482,
            5
        ],
        "location_end_shuttle": [
            201,
            1617,
            0
        ],
        "location_Init_start_top": [
            [
                361,
                409
            ],
            [
                328,
                432
            ]
        ],
        "location_Init_start_bottom": [
            [
                306,
                869
            ],
            [
                245,
                861
            ]
        ],
        "location_Init_end_top": [
            [
                313,
                550
            ],
            [
                296,
                518
            ]
        ],
        "location_Init_end_bottom": [
            [
                313,
                869
            ],
            [
                412,
                877
            ]
        ]
    },
    "18": {
        "current_set": 1,
        "sides_changed": 0,
        "Action_FB_init_bottom": "Forehand",
        "Action_wl_init_bottom": "Mistake",
        "shot": "Net Shot",
        "current_rally_top_init_score": 1,
        "current_rally_bottom_init_score": 0,
        "current_set_top_init_score": 9,
        "current_set_bottom_init_score": 9,
        "location_contact_shuttle": [
            299,
            1442,
            5
        ],
        "location_end_shuttle": [
            483,
            266,
            0
        ],
        "location_Init_start_top": -1,
        "location_Init_start_bottom": -1,
        "location_Init_end_top": -1,
        "location_Init_end_bottom": -1
    },
    "19": {
        "current_set": 1,
        "sides_changed": 0,
        "Action_FB_init_top": "Forehand",
        "Action_wl_init_top": "Winner",
        "Action_FB_init_bottom": "Backhand",
        "Action_wl_init_bottom": "Mistake",
        "shot": "Placement",
        "current_rally_top_init_score": 1,
        "current_rally_bottom_init_score": 0,
        "current_set_top_init_score": 10,
        "current_set_bottom_init_score": 9,
        "location_contact_shuttle": [
            353,
            742,
            5
        ],
        "location_end_shuttle": [
            435,
            1392,
            0
        ],
        "location_Init_start_top": -1,
        "location_Init_start_bottom": -1,
        "location_Init_end_top": -1,
        "location_Init_end_bottom": -1
    },
    "20": {
        "current_set": 1,
        "sides_changed": 0,
        "Action_FB_init_top": "Forehand",
        "Action_wl_init_top": "Mistake",
        "shot": "Net Shot",
        "current_rally_top_init_score": 0,
        "current_rally_bottom_init_score": 1,
        "current_set_top_init_score": 10,
        "current_set_bottom_init_score": 10,
        "location_contact_shuttle": [
            313,
            443,
            5
        ],
        "location_end_shuttle": [
            231,
            297,
            0
        ],
        "location_Init_start_top": [
            [
                606,
                729
            ],
            [
                572,
                720
            ]
        ],
        "location_Init_start_bottom": -1,
        "location_Init_end_top": -1,
        "location_Init_end_bottom": -1
    },
    "21": {
        "current_set": 1,
        "sides_changed": 0,
        "Action_FB_init_bottom": "Backhand",
        "Action_wl_init_bottom": "Mistake",
        "shot": "Placement",
        "current_rally_top_init_score": 1,
        "current_rally_bottom_init_score": 0,
        "current_set_top_init_score": 11,
        "current_set_bottom_init_score": 10,
        "location_contact_shuttle": [
            258,
            1170,
            5
        ],
        "location_end_shuttle": [
            691,
            241,
            0
        ],
        "location_Init_start_top": [
            [
                289,
                291
            ],
            [
                273,
                303
            ]
        ],
        "location_Init_start_bottom": [
            [
                287,
                981
            ],
            [
                310,
                988
            ]
        ],
        "location_Init_end_top": [
            [
                290,
                31
            ],
            [
                275,
                45
            ]
        ],
        "location_Init_end_bottom": [
            [
                203,
                877
            ],
            [
                222,
                931
            ]
        ]
    },
    "22": {
        "current_set": 1,
        "sides_changed": 0,
        "Action_FB_init_bottom": "Forehand",
        "Action_wl_init_bottom": "Winner",
        "shot": "Placement",
        "current_rally_top_init_score": 0,
        "current_rally_bottom_init_score": 1,
        "current_set_top_init_score": 11,
        "current_set_bottom_init_score": 11,
        "location_contact_shuttle": [
            269,
            1425,
            5
        ],
        "location_end_shuttle": [
            230,
            432,
            0
        ],
        "location_Init_start_top": [
            [
                379,
                476
            ],
            [
                363,
                443
            ]
        ],
        "location_Init_start_bottom": [
            [
                485,
                1114
            ],
            [
                506,
                1162
            ]
        ],
        "location_Init_end_top": [
            [
                379,
                465
            ],
            [
                363,
                443
            ]
        ],
        "location_Init_end_bottom": [
            [
                487,
                1107
            ],
            [
                503,
                1156
            ]
        ]
    },
    "23": {
        "current_set": 1,
        "sides_changed": 0,
        "Action_FB_init_bottom": "Forehand",
        "Action_wl_init_bottom": "Winner",
        "shot": "Placement",
        "current_rally_top_init_score": 0,
        "current_rally_bottom_init_score": 1,
        "current_set_top_init_score": 11,
        "current_set_bottom_init_score": 12,
        "location_contact_shuttle": [
            649,
            1503,
            5
        ],
        "location_end_shuttle": [
            365,
            339,
            0
        ],
        "location_Init_start_top": -1,
        "location_Init_start_bottom": -1,
        "location_Init_end_top": -1,
        "location_Init_end_bottom": -1
    },
    "24": {
        "current_set": 1,
        "sides_changed": 0,
        "Action_FB_init_bottom": "Backhand",
        "Action_wl_init_bottom": "Mistake",
        "shot": "Net Shot",
        "current_rally_top_init_score": 1,
        "current_rally_bottom_init_score": 0,
        "current_set_top_init_score": 12,
        "current_set_bottom_init_score": 12,
        "location_contact_shuttle": [
            270,
            1440,
            5
        ],
        "location_end_shuttle": [
            238,
            222,
            0
        ],
        "location_Init_start_top": -1,
        "location_Init_start_bottom": -1,
        "location_Init_end_top": [
            [
                156,
                16
            ],
            [
                149,
                -12
            ]
        ],
        "location_Init_end_bottom": -1
    },
    "25": {
        "current_set": 1,
        "sides_changed": 0,
        "Action_FB_init_top": "Forehand",
        "Action_wl_init_top": "Mistake",
        "shot": "Placement",
        "current_rally_top_init_score": 0,
        "current_rally_bottom_init_score": 1,
        "current_set_top_init_score": 12,
        "current_set_bottom_init_score": 13,
        "location_contact_shuttle": [
            300,
            630,
            5
        ],
        "location_end_shuttle": [
            774,
            1481,
            0
        ],
        "location_Init_start_top": -1,
        "location_Init_start_bottom": -1,
        "location_Init_end_top": -1,
        "location_Init_end_bottom": -1
    },
    "26": {
        "current_set": 1,
        "sides_changed": 0,
        "Action_FB_init_top": "Forehand",
        "Action_wl_init_top": "Winner",
        "shot": "Placement",
        "current_rally_top_init_score": 1,
        "current_rally_bottom_init_score": 0,
        "current_set_top_init_score": 13,
        "current_set_bottom_init_score": 13,
        "location_contact_shuttle": [
            692,
            571,
            5
        ],
        "location_end_shuttle": [
            286,
            1291,
            0
        ],
        "location_Init_start_top": [
            [
                523,
                143
            ],
            [
                481,
                129
            ]
        ],
        "location_Init_start_bottom": [
            [
                385,
                1113
            ],
            [
                438,
                1114
            ]
        ],
        "location_Init_end_top": [
            [
                447,
                129
            ],
            [
                419,
                143
            ]
        ],
        "location_Init_end_bottom": [
            [
                358,
                1126
            ],
            [
                465,
                1107
            ]
        ]
    },
    "27": {
        "current_set": 1,
        "sides_changed": 0,
        "Action_FB_init_bottom": "Forehand",
        "Action_wl_init_bottom": "Winner",
        "shot": "Placement",
        "current_rally_top_init_score": 0,
        "current_rally_bottom_init_score": 1,
        "current_set_top_init_score": 13,
        "current_set_bottom_init_score": 14,
        "location_contact_shuttle": [
            371,
            1351,
            5
        ],
        "location_end_shuttle": [
            648,
            683,
            0
        ],
        "location_Init_start_top": [
            [
                521,
                519
            ],
            [
                481,
                498
            ]
        ],
        "location_Init_start_bottom": [
            [
                385,
                1228
            ],
            [
                422,
                1205
            ]
        ],
        "location_Init_end_top": [
            [
                433,
                409
            ],
            [
                430,
                409
            ]
        ],
        "location_Init_end_bottom": [
            [
                396,
                1374
            ],
            [
                431,
                1414
            ]
        ]
    },
    "28": {
        "current_set": 1,
        "sides_changed": 0,
        "Action_FB_init_bottom": "Forehand",
        "Action_wl_init_bottom": "Mistake",
        "shot": "Placement",
        "current_rally_top_init_score": 1,
        "current_rally_bottom_init_score": 0,
        "current_set_top_init_score": 14,
        "current_set_bottom_init_score": 14,
        "location_contact_shuttle": [
            251,
            1370,
            5
        ],
        "location_end_shuttle": [
            311,
            266,
            0
        ],
        "location_Init_start_top": -1,
        "location_Init_start_bottom": -1,
        "location_Init_end_top": -1,
        "location_Init_end_bottom": -1
    },
    "29": {
        "current_set": 1,
        "sides_changed": 0,
        "Action_FB_init_top": "Backhand",
        "Action_wl_init_top": "Mistake",
        "Action_FB_init_bottom": "Forehand",
        "Action_wl_init_bottom": "Winner",
        "shot": "Placement",
        "current_rally_top_init_score": 0,
        "current_rally_bottom_init_score": 1,
        "current_set_top_init_score": 14,
        "current_set_bottom_init_score": 15,
        "location_contact_shuttle": [
            320,
            1498,
            5
        ],
        "location_end_shuttle": [
            593,
            621,
            0
        ],
        "location_Init_start_top": -1,
        "location_Init_start_bottom": -1,
        "location_Init_end_top": -1,
        "location_Init_end_bottom": -1
    },
    "30": {
        "current_set": 1,
        "sides_changed": 0,
        "Action_FB_init_bottom": "Forehand",
        "Action_wl_init_bottom": "Winner",
        "shot": "Placement",
        "current_rally_top_init_score": 0,
        "current_rally_bottom_init_score": 1,
        "current_set_top_init_score": 14,
        "current_set_bottom_init_score": 16,
        "location_contact_shuttle": [
            287,
            1487,
            5
        ],
        "location_end_shuttle": [
            249,
            351,
            0
        ],
        "location_Init_start_top": -1,
        "location_Init_start_bottom": -1,
        "location_Init_end_top": -1,
        "location_Init_end_bottom": -1
    },
    "31": {
        "current_set": 1,
        "sides_changed": 0,
        "Action_FB_init_top": "Forehand",
        "Action_wl_init_top": "Winner",
        "Action_FB_init_bottom": "Forehand",
        "Action_wl_init_bottom": "Mistake",
        "shot": "Placement",
        "current_rally_top_init_score": 1,
        "current_rally_bottom_init_score": 0,
        "current_set_top_init_score": 15,
        "current_set_bottom_init_score": 16,
        "location_contact_shuttle": [
            269,
            768,
            5
        ],
        "location_end_shuttle": [
            682,
            1071,
            0
        ],
        "location_Init_start_top": -1,
        "location_Init_start_bottom": -1,
        "location_Init_end_top": -1,
        "location_Init_end_bottom": -1
    },
    "32": {
        "current_set": 1,
        "sides_changed": 0,
        "Action_FB_init_top": "Forehand",
        "Action_wl_init_top": "Mistake",
        "shot": "Placement",
        "current_rally_top_init_score": 0,
        "current_rally_bottom_init_score": 1,
        "current_set_top_init_score": 15,
        "current_set_bottom_init_score": 17,
        "location_contact_shuttle": [
            711,
            466,
            5
        ],
        "location_end_shuttle": [
            755,
            1222,
            0
        ],
        "location_Init_start_top": -1,
        "location_Init_start_bottom": -1,
        "location_Init_end_top": -1,
        "location_Init_end_bottom": -1
    },
    "33": {
        "current_set": 1,
        "sides_changed": 0,
        "Action_FB_init_top": "Backhand",
        "Action_wl_init_top": "Mistake",
        "shot": "Net Shot",
        "current_rally_top_init_score": 0,
        "current_rally_bottom_init_score": 1,
        "current_set_top_init_score": 15,
        "current_set_bottom_init_score": 18,
        "location_contact_shuttle": [
            641,
            808,
            5
        ],
        "location_end_shuttle": [
            374,
            241,
            0
        ],
        "location_Init_start_top": [
            [
                362,
                303
            ],
            [
                329,
                363
            ]
        ],
        "location_Init_start_bottom": [
            [
                237,
                1052
            ],
            [
                214,
                1002
            ]
        ],
        "location_Init_end_top": [
            [
                291,
                420
            ],
            [
                266,
                420
            ]
        ],
        "location_Init_end_bottom": [
            [
                296,
                1100
            ],
            [
                341,
                1052
            ]
        ]
    },
    "34": {
        "current_set": 2,
        "sides_changed": 0,
        "Action_FB_init_top": "Forehand",
        "Action_wl_init_top": "Mistake",
        "shot": "Net Shot",
        "current_rally_top_init_score": 0,
        "current_rally_bottom_init_score": 1,
        "current_set_top_init_score": 0,
        "current_set_bottom_init_score": 1,
        "location_contact_shuttle": [
            669,
            1200,
            5
        ],
        "location_end_shuttle": [
            632,
            291,
            0
        ],
        "location_Init_start_top": [
            [
                475,
                982
            ],
            [
                493,
                1032
            ]
        ],
        "location_Init_start_bottom": [
            [
                545,
                566
            ],
            [
                550,
                556
            ]
        ],
        "location_Init_end_top": [
            [
                474,
                996
            ],
            [
                499,
                978
            ]
        ],
        "location_Init_end_bottom": [
            [
                578,
                664
            ],
            [
                547,
                674
            ]
        ]
    },
    "35": {
        "current_set": 2,
        "sides_changed": 0,
        "Action_FB_init_top": "Forehand",
        "Action_wl_init_top": "Mistake",
        "shot": "Net Shot",
        "current_rally_top_init_score": 0,
        "current_rally_bottom_init_score": 1,
        "current_set_top_init_score": 0,
        "current_set_bottom_init_score": 2,
        "location_contact_shuttle": [
            655,
            1384,
            5
        ],
        "location_end_shuttle": [
            714,
            298,
            0
        ],
        "location_Init_start_top": [
            [
                521,
                1053
            ],
            [
                508,
                1060
            ]
        ],
        "location_Init_start_bottom": -1,
        "location_Init_end_top": [
            [
                520,
                1067
            ],
            [
                465,
                1060
            ]
        ],
        "location_Init_end_bottom": -1
    },
    "36": {
        "current_set": 2,
        "sides_changed": 0,
        "Action_FB_init_top": "Forehand",
        "Action_wl_init_top": "Mistake",
        "shot": "Placement",
        "current_rally_top_init_score": 0,
        "current_rally_bottom_init_score": 1,
        "current_set_top_init_score": 0,
        "current_set_bottom_init_score": 3,
        "location_contact_shuttle": [
            589,
            1503,
            5
        ],
        "location_end_shuttle": [
            796,
            520,
            0
        ],
        "location_Init_start_top": [
            [
                463,
                1168
            ],
            [
                565,
                1200
            ]
        ],
        "location_Init_start_bottom": [
            [
                544,
                340
            ],
            [
                452,
                351
            ]
        ],
        "location_Init_end_top": [
            [
                381,
                1113
            ],
            [
                423,
                1149
            ]
        ],
        "location_Init_end_bottom": [
            [
                330,
                272
            ],
            [
                284,
                235
            ]
        ]
    },
    "37": {
        "current_set": 2,
        "sides_changed": 0,
        "Action_FB_init_top": "Forehand",
        "Action_wl_init_top": "Mistake",
        "shot": "Placement",
        "current_rally_top_init_score": 0,
        "current_rally_bottom_init_score": 1,
        "current_set_top_init_score": 0,
        "current_set_bottom_init_score": 4,
        "location_contact_shuttle": [
            343,
            1531,
            5
        ],
        "location_end_shuttle": [
            266,
            291,
            0
        ],
        "location_Init_start_top": [
            [
                395,
                1053
            ],
            [
                468,
                974
            ]
        ],
        "location_Init_start_bottom": [
            [
                453,
                303
            ],
            [
                429,
                328
            ]
        ],
        "location_Init_end_top": [
            [
                465,
                1053
            ],
            [
                474,
                1094
            ]
        ],
        "location_Init_end_bottom": [
            [
                495,
                222
            ],
            [
                493,
                222
            ]
        ]
    },
    "38": {
        "current_set": 2,
        "sides_changed": 0,
        "Action_FB_init_top": "Backhand",
        "Action_wl_init_top": "Winner",
        "shot": "Placement",
        "current_rally_top_init_score": 1,
        "current_rally_bottom_init_score": 0,
        "current_set_top_init_score": 1,
        "current_set_bottom_init_score": 4,
        "location_contact_shuttle": [
            271,
            1142,
            5
        ],
        "location_end_shuttle": [
            468,
            625,
            0
        ],
        "location_Init_start_top": -1,
        "location_Init_start_bottom": -1,
        "location_Init_end_top": [
            [
                280,
                1411
            ],
            [
                344,
                1358
            ]
        ],
        "location_Init_end_bottom": -1
    },
    "39": {
        "current_set": 2,
        "sides_changed": 0,
        "Action_FB_init_top": "Forehand",
        "Action_wl_init_top": "Mistake",
        "shot": "Placement",
        "current_rally_top_init_score": 0,
        "current_rally_bottom_init_score": 1,
        "current_set_top_init_score": 1,
        "current_set_bottom_init_score": 5,
        "location_contact_shuttle": [
            218,
            1568,
            5
        ],
        "location_end_shuttle": [
            204,
            278,
            0
        ],
        "location_Init_start_top": -1,
        "location_Init_start_bottom": -1,
        "location_Init_end_top": -1,
        "location_Init_end_bottom": -1
    },
    "40": {
        "current_set": 2,
        "sides_changed": 0,
        "Action_FB_init_top": "Forehand",
        "Action_wl_init_top": "Winner",
        "shot": "Placement",
        "current_rally_top_init_score": 1,
        "current_rally_bottom_init_score": 0,
        "current_set_top_init_score": 2,
        "current_set_bottom_init_score": 5,
        "location_contact_shuttle": [
            595,
            1344,
            5
        ],
        "location_end_shuttle": [
            529,
            392,
            0
        ],
        "location_Init_start_top": [
            [
                364,
                1155
            ],
            [
                397,
                1133
            ]
        ],
        "location_Init_start_bottom": [
            [
                285,
                88
            ],
            [
                279,
                59
            ]
        ],
        "location_Init_end_top": [
            [
                327,
                1155
            ],
            [
                435,
                1155
            ]
        ],
        "location_Init_end_bottom": [
            [
                305,
                222
            ],
            [
                261,
                129
            ]
        ]
    },
    "41": {
        "current_set": 2,
        "sides_changed": 0,
        "Action_FB_init_bottom": "Forehand",
        "Action_wl_init_bottom": "Winner",
        "shot": "Placement",
        "current_rally_top_init_score": 0,
        "current_rally_bottom_init_score": 1,
        "current_set_top_init_score": 2,
        "current_set_bottom_init_score": 6,
        "location_contact_shuttle": [
            448,
            443,
            5
        ],
        "location_end_shuttle": [
            285,
            1457,
            0
        ],
        "location_Init_start_top": -1,
        "location_Init_start_bottom": -1,
        "location_Init_end_top": -1,
        "location_Init_end_bottom": -1
    },
    "42": {
        "current_set": 2,
        "sides_changed": 0,
        "Action_FB_init_top": "Forehand",
        "Action_wl_init_top": "Winner",
        "shot": "Placement",
        "current_rally_top_init_score": 1,
        "current_rally_bottom_init_score": 0,
        "current_set_top_init_score": 3,
        "current_set_bottom_init_score": 6,
        "location_contact_shuttle": [
            531,
            1520,
            5
        ],
        "location_end_shuttle": [
            225,
            437,
            0
        ],
        "location_Init_start_top": -1,
        "location_Init_start_bottom": -1,
        "location_Init_end_top": -1,
        "location_Init_end_bottom": -1
    },
    "43": {
        "current_set": 2,
        "sides_changed": 0,
        "Action_FB_init_bottom": "Backhand",
        "Action_wl_init_bottom": "Mistake",
        "shot": "Net Shot",
        "current_rally_top_init_score": 1,
        "current_rally_bottom_init_score": 0,
        "current_set_top_init_score": 4,
        "current_set_bottom_init_score": 6,
        "location_contact_shuttle": [
            702,
            591,
            5
        ],
        "location_end_shuttle": [
            766,
            525,
            0
        ],
        "location_Init_start_top": [
            [
                283,
                1179
            ],
            [
                303,
                1198
            ]
        ],
        "location_Init_start_bottom": [
            [
                423,
                476
            ],
            [
                411,
                432
            ]
        ],
        "location_Init_end_top": [
            [
                251,
                1393
            ],
            [
                275,
                1383
            ]
        ],
        "location_Init_end_bottom": [
            [
                434,
                351
            ],
            [
                379,
                409
            ]
        ]
    },
    "44": {
        "current_set": 2,
        "sides_changed": 0,
        "Action_FB_init_top": "Backhand",
        "Action_wl_init_top": "Mistake",
        "shot": "Net Shot",
        "current_rally_top_init_score": 0,
        "current_rally_bottom_init_score": 1,
        "current_set_top_init_score": 4,
        "current_set_bottom_init_score": 7,
        "location_contact_shuttle": [
            340,
            1381,
            5
        ],
        "location_end_shuttle": [
            317,
            247,
            0
        ],
        "location_Init_start_top": -1,
        "location_Init_start_bottom": -1,
        "location_Init_end_top": -1,
        "location_Init_end_bottom": -1
    },
    "45": {
        "current_set": 2,
        "sides_changed": 0,
        "Action_FB_init_bottom": "Backhand",
        "Action_wl_init_bottom": "Winner",
        "shot": "Placement",
        "current_rally_top_init_score": 0,
        "current_rally_bottom_init_score": 1,
        "current_set_top_init_score": 4,
        "current_set_bottom_init_score": 8,
        "location_contact_shuttle": [
            634,
            679,
            5
        ],
        "location_end_shuttle": [
            347,
            951,
            0
        ],
        "location_Init_start_top": [
            [
                380,
                1149
            ],
            [
                438,
                1114
            ]
        ],
        "location_Init_start_bottom": [
            [
                553,
                209
            ],
            [
                553,
                196
            ]
        ],
        "location_Init_end_top": [
            [
                390,
                1100
            ],
            [
                443,
                1114
            ]
        ],
        "location_Init_end_bottom": [
            [
                650,
                45
            ],
            [
                614,
                45
            ]
        ]
    },
    "46": {
        "current_set": 2,
        "sides_changed": 0,
        "Action_FB_init_top": "Forehand",
        "Action_wl_init_top": "Winner",
        "Action_FB_init_bottom": "Forehand",
        "Action_wl_init_bottom": "Mistake",
        "shot": "Placement",
        "current_rally_top_init_score": 1,
        "current_rally_bottom_init_score": 0,
        "current_set_top_init_score": 5,
        "current_set_bottom_init_score": 8,
        "location_contact_shuttle": [
            623,
            1428,
            5
        ],
        "location_end_shuttle": [
            523,
            566,
            0
        ],
        "location_Init_start_top": -1,
        "location_Init_start_bottom": -1,
        "location_Init_end_top": -1,
        "location_Init_end_bottom": -1
    },
    "47": {
        "current_set": 2,
        "sides_changed": 0,
        "Action_FB_init_top": "Forehand",
        "Action_wl_init_top": "Mistake",
        "shot": "Placement",
        "current_rally_top_init_score": 0,
        "current_rally_bottom_init_score": 1,
        "current_set_top_init_score": 5,
        "current_set_bottom_init_score": 9,
        "location_contact_shuttle": [
            339,
            1576,
            5
        ],
        "location_end_shuttle": [
            190,
            303,
            0
        ],
        "location_Init_start_top": [
            [
                392,
                1199
            ],
            [
                422,
                1149
            ]
        ],
        "location_Init_start_bottom": [
            [
                535,
                508
            ],
            [
                496,
                508
            ]
        ],
        "location_Init_end_top": [
            [
                256,
                1251
            ],
            [
                293,
                1299
            ]
        ],
        "location_Init_end_bottom": [
            [
                435,
                421
            ],
            [
                379,
                398
            ]
        ]
    },
    "48": {
        "current_set": 2,
        "sides_changed": 0,
        "Action_FB_init_top": "Forehand",
        "Action_wl_init_top": "Mistake",
        "shot": "Net Shot",
        "current_rally_top_init_score": 0,
        "current_rally_bottom_init_score": 1,
        "current_set_top_init_score": 5,
        "current_set_bottom_init_score": 10,
        "location_contact_shuttle": [
            523,
            1264,
            5
        ],
        "location_end_shuttle": [
            538,
            222,
            0
        ],
        "location_Init_start_top": -1,
        "location_Init_start_bottom": -1,
        "location_Init_end_top": -1,
        "location_Init_end_bottom": -1
    },
    "49": {
        "current_set": 2,
        "sides_changed": 0,
        "Action_FB_init_bottom": "Backhand",
        "Action_wl_init_bottom": "Winner",
        "shot": "Placement",
        "current_rally_top_init_score": 0,
        "current_rally_bottom_init_score": 1,
        "current_set_top_init_score": 5,
        "current_set_bottom_init_score": 11,
        "location_contact_shuttle": [
            670,
            787,
            5
        ],
        "location_end_shuttle": [
            718,
            1521,
            0
        ],
        "location_Init_start_top": -1,
        "location_Init_start_bottom": -1,
        "location_Init_end_top": [
            [
                415,
                1488
            ],
            [
                234,
                1468
            ]
        ],
        "location_Init_end_bottom": -1
    },
    "50": {
        "current_set": 2,
        "sides_changed": 0,
        "Action_FB_init_bottom": "Backhand",
        "Action_wl_init_bottom": "Mistake",
        "shot": "Net Shot",
        "current_rally_top_init_score": 1,
        "current_rally_bottom_init_score": 0,
        "current_set_top_init_score": 6,
        "current_set_bottom_init_score": 11,
        "location_contact_shuttle": [
            531,
            626,
            5
        ],
        "location_end_shuttle": [
            392,
            415,
            0
        ],
        "location_Init_start_top": [
            [
                370,
                1149
            ],
            [
                538,
                1181
            ]
        ],
        "location_Init_start_bottom": [
            [
                503,
                196
            ],
            [
                435,
                260
            ]
        ],
        "location_Init_end_top": [
            [
                422,
                1155
            ],
            [
                449,
                1149
            ]
        ],
        "location_Init_end_bottom": [
            [
                557,
                432
            ],
            [
                562,
                432
            ]
        ]
    },
    "51": {
        "current_set": 2,
        "sides_changed": 0,
        "Action_FB_init_top": "Forehand",
        "Action_wl_init_top": "Winner",
        "shot": "Placement",
        "current_rally_top_init_score": 1,
        "current_rally_bottom_init_score": 0,
        "current_set_top_init_score": 7,
        "current_set_bottom_init_score": 11,
        "location_contact_shuttle": [
            635,
            1419,
            5
        ],
        "location_end_shuttle": [
            755,
            375,
            0
        ],
        "location_Init_start_top": [
            [
                282,
                1257
            ],
            [
                379,
                1277
            ]
        ],
        "location_Init_start_bottom": -1,
        "location_Init_end_top": [
            [
                211,
                1293
            ],
            [
                342,
                1310
            ]
        ],
        "location_Init_end_bottom": -1
    },
    "52": {
        "current_set": 2,
        "sides_changed": 0,
        "Action_FB_init_bottom": "Backhand",
        "Action_wl_init_bottom": "Mistake",
        "shot": "Placement",
        "current_rally_top_init_score": 1,
        "current_rally_bottom_init_score": 0,
        "current_set_top_init_score": 8,
        "current_set_bottom_init_score": 11,
        "location_contact_shuttle": [
            673,
            641,
            5
        ],
        "location_end_shuttle": [
            780,
            279,
            0
        ],
        "location_Init_start_top": -1,
        "location_Init_start_bottom": -1,
        "location_Init_end_top": -1,
        "location_Init_end_bottom": -1
    },
    "53": {
        "current_set": 2,
        "sides_changed": 0,
        "Action_FB_init_bottom": "Backhand",
        "Action_wl_init_bottom": "Mistake",
        "shot": "Placement",
        "current_rally_top_init_score": 1,
        "current_rally_bottom_init_score": 0,
        "current_set_top_init_score": 9,
        "current_set_bottom_init_score": 11,
        "location_contact_shuttle": [
            619,
            631,
            5
        ],
        "location_end_shuttle": [
            768,
            1222,
            0
        ],
        "location_Init_start_top": [
            [
                466,
                1252
            ],
            [
                443,
                1180
            ]
        ],
        "location_Init_start_bottom": [
            [
                535,
                170
            ],
            [
                579,
                143
            ]
        ],
        "location_Init_end_top": [
            [
                368,
                1093
            ],
            [
                458,
                1143
            ]
        ],
        "location_Init_end_bottom": [
            [
                596,
                102
            ],
            [
                513,
                143
            ]
        ]
    },
    "54": {
        "current_set": 2,
        "sides_changed": 0,
        "Action_FB_init_top": "Backhand",
        "Action_wl_init_top": "Mistake",
        "Action_FB_init_bottom": "Forehand",
        "Action_wl_init_bottom": "Winner",
        "shot": "Placement",
        "current_rally_top_init_score": 0,
        "current_rally_bottom_init_score": 1,
        "current_set_top_init_score": 9,
        "current_set_bottom_init_score": 12,
        "location_contact_shuttle": [
            668,
            546,
            5
        ],
        "location_end_shuttle": [
            269,
            1257,
            0
        ],
        "location_Init_start_top": [
            [
                334,
                1031
            ],
            [
                339,
                1045
            ]
        ],
        "location_Init_start_bottom": [
            [
                594,
                183
            ],
            [
                561,
                235
            ]
        ],
        "location_Init_end_top": -1,
        "location_Init_end_bottom": -1
    },
    "55": {
        "current_set": 2,
        "sides_changed": 0,
        "Action_FB_init_bottom": "Forehand",
        "Action_wl_init_bottom": "Winner",
        "shot": "Placement",
        "current_rally_top_init_score": 0,
        "current_rally_bottom_init_score": 1,
        "current_set_top_init_score": 9,
        "current_set_bottom_init_score": 13,
        "location_contact_shuttle": [
            719,
            520,
            5
        ],
        "location_end_shuttle": [
            703,
            1562,
            0
        ],
        "location_Init_start_top": -1,
        "location_Init_start_bottom": -1,
        "location_Init_end_top": -1,
        "location_Init_end_bottom": -1
    },
    "56": {
        "current_set": 2,
        "sides_changed": 0,
        "Action_FB_init_top": "Forehand",
        "Action_wl_init_top": "Mistake",
        "shot": "Placement",
        "current_rally_top_init_score": 0,
        "current_rally_bottom_init_score": 1,
        "current_set_top_init_score": 9,
        "current_set_bottom_init_score": 14,
        "location_contact_shuttle": [
            624,
            1476,
            5
        ],
        "location_end_shuttle": [
            790,
            582,
            0
        ],
        "location_Init_start_top": [
            [
                341,
                1106
            ],
            [
                429,
                1003
            ]
        ],
        "location_Init_start_bottom": [
            [
                462,
                586
            ],
            [
                551,
                606
            ]
        ],
        "location_Init_end_top": [
            [
                487,
                989
            ],
            [
                551,
                878
            ]
        ],
        "location_Init_end_bottom": [
            [
                505,
                454
            ],
            [
                492,
                443
            ]
        ]
    },
    "57": {
        "current_set": 2,
        "sides_changed": 0,
        "Action_FB_init_top": "Forehand",
        "Action_wl_init_top": "Mistake",
        "shot": "Placement",
        "current_rally_top_init_score": 0,
        "current_rally_bottom_init_score": 1,
        "current_set_top_init_score": 9,
        "current_set_bottom_init_score": 15,
        "location_contact_shuttle": [
            640,
            1221,
            5
        ],
        "location_end_shuttle": [
            741,
            279,
            0
        ],
        "location_Init_start_top": [
            [
                397,
                1252
            ],
            [
                400,
                1252
            ]
        ],
        "location_Init_start_bottom": [
            [
                570,
                375
            ],
            [
                563,
                410
            ]
        ],
        "location_Init_end_top": -1,
        "location_Init_end_bottom": -1
    },
    "58": {
        "current_set": 2,
        "sides_changed": 0,
        "Action_FB_init_top": "Backhand",
        "Action_wl_init_top": "Winner",
        "shot": "Placement",
        "current_rally_top_init_score": 1,
        "current_rally_bottom_init_score": 0,
        "current_set_top_init_score": 10,
        "current_set_bottom_init_score": 15,
        "location_contact_shuttle": [
            389,
            1103,
            5
        ],
        "location_end_shuttle": [
            557,
            941,
            0
        ],
        "location_Init_start_top": [
            [
                123,
                1372
            ],
            [
                354,
                1369
            ]
        ],
        "location_Init_start_bottom": [
            [
                236,
                386
            ],
            [
                245,
                351
            ]
        ],
        "location_Init_end_top": [
            [
                132,
                1367
            ],
            [
                346,
                1348
            ]
        ],
        "location_Init_end_bottom": -1
    },
    "59": {
        "current_set": 2,
        "sides_changed": 0,
        "Action_FB_init_bottom": "Forehand",
        "Action_wl_init_bottom": "Mistake",
        "shot": "Placement",
        "current_rally_top_init_score": 1,
        "current_rally_bottom_init_score": 0,
        "current_set_top_init_score": 11,
        "current_set_bottom_init_score": 15,
        "location_contact_shuttle": [
            372,
            820,
            5
        ],
        "location_end_shuttle": [
            161,
            1551,
            0
        ],
        "location_Init_start_top": -1,
        "location_Init_start_bottom": -1,
        "location_Init_end_top": -1,
        "location_Init_end_bottom": -1
    },
    "60": {
        "current_set": 2,
        "sides_changed": 0,
        "Action_FB_init_top": "Backhand",
        "Action_wl_init_top": "Mistake",
        "shot": "Net Shot",
        "current_rally_top_init_score": 0,
        "current_rally_bottom_init_score": 1,
        "current_set_top_init_score": 11,
        "current_set_bottom_init_score": 16,
        "location_contact_shuttle": [
            273,
            1279,
            5
        ],
        "location_end_shuttle": [
            556,
            328,
            0
        ],
        "location_Init_start_top": [
            [
                335,
                1283
            ],
            [
                383,
                1211
            ]
        ],
        "location_Init_start_bottom": [
            [
                453,
                432
            ],
            [
                561,
                443
            ]
        ],
        "location_Init_end_top": [
            [
                463,
                1060
            ],
            [
                546,
                918
            ]
        ],
        "location_Init_end_bottom": [
            [
                486,
                340
            ],
            [
                488,
                351
            ]
        ]
    },
    "61": {
        "current_set": 2,
        "sides_changed": 0,
        "Action_FB_init_top": "Forehand",
        "Action_wl_init_top": "Winner",
        "shot": "Placement",
        "current_rally_top_init_score": 1,
        "current_rally_bottom_init_score": 0,
        "current_set_top_init_score": 12,
        "current_set_bottom_init_score": 16,
        "location_contact_shuttle": [
            271,
            1468,
            5
        ],
        "location_end_shuttle": [
            233,
            398,
            0
        ],
        "location_Init_start_top": -1,
        "location_Init_start_bottom": -1,
        "location_Init_end_top": -1,
        "location_Init_end_bottom": -1
    },
    "62": {
        "current_set": 2,
        "sides_changed": 0,
        "Action_FB_init_bottom": "Forehand",
        "Action_wl_init_bottom": "Mistake",
        "shot": "Placement",
        "current_rally_top_init_score": 1,
        "current_rally_bottom_init_score": 0,
        "current_set_top_init_score": 13,
        "current_set_bottom_init_score": 16,
        "location_contact_shuttle": [
            399,
            803,
            5
        ],
        "location_end_shuttle": [
            183,
            1530,
            0
        ],
        "location_Init_start_top": -1,
        "location_Init_start_bottom": -1,
        "location_Init_end_top": -1,
        "location_Init_end_bottom": -1
    },
    "63": {
        "current_set": 2,
        "sides_changed": 0,
        "Action_FB_init_bottom": "Forehand",
        "Action_wl_init_bottom": "Mistake",
        "shot": "Placement",
        "current_rally_top_init_score": 1,
        "current_rally_bottom_init_score": 0,
        "current_set_top_init_score": 14,
        "current_set_bottom_init_score": 16,
        "location_contact_shuttle": [
            477,
            519,
            5
        ],
        "location_end_shuttle": [
            842,
            1408,
            0
        ],
        "location_Init_start_top": -1,
        "location_Init_start_bottom": -1,
        "location_Init_end_top": -1,
        "location_Init_end_bottom": -1
    },
    "64": {
        "current_set": 2,
        "sides_changed": 0,
        "Action_FB_init_top": "Forehand",
        "Action_wl_init_top": "Mistake",
        "shot": "Placement",
        "current_rally_top_init_score": 0,
        "current_rally_bottom_init_score": 1,
        "current_set_top_init_score": 14,
        "current_set_bottom_init_score": 17,
        "location_contact_shuttle": [
            326,
            1371,
            5
        ],
        "location_end_shuttle": [
            199,
            420,
            0
        ],
        "location_Init_start_top": -1,
        "location_Init_start_bottom": -1,
        "location_Init_end_top": -1,
        "location_Init_end_bottom": -1
    },
    "65": {
        "current_set": 2,
        "sides_changed": 0,
        "Action_FB_init_bottom": "Backhand",
        "Action_wl_init_bottom": "Winner",
        "shot": "Placement",
        "current_rally_top_init_score": 0,
        "current_rally_bottom_init_score": 1,
        "current_set_top_init_score": 14,
        "current_set_bottom_init_score": 18,
        "location_contact_shuttle": [
            675,
            791,
            5
        ],
        "location_end_shuttle": [
            666,
            1547,
            0
        ],
        "location_Init_start_top": [
            [
                366,
                1155
            ],
            [
                462,
                1149
            ]
        ],
        "location_Init_start_bottom": [
            [
                571,
                143
            ],
            [
                463,
                102
            ]
        ],
        "location_Init_end_top": [
            [
                343,
                1149
            ],
            [
                332,
                1106
            ]
        ],
        "location_Init_end_bottom": [
            [
                498,
                285
            ],
            [
                420,
                272
            ]
        ]
    },
    "66": {
        "current_set": 2,
        "sides_changed": 0,
        "Action_FB_init_top": "Forehand",
        "Action_wl_init_top": "Mistake",
        "shot": "Placement",
        "current_rally_top_init_score": 0,
        "current_rally_bottom_init_score": 1,
        "current_set_top_init_score": 14,
        "current_set_bottom_init_score": 19,
        "location_contact_shuttle": [
            309,
            1584,
            5
        ],
        "location_end_shuttle": [
            278,
            279,
            0
        ],
        "location_Init_start_top": -1,
        "location_Init_start_bottom": -1,
        "location_Init_end_top": -1,
        "location_Init_end_bottom": -1
    },
    "67": {
        "current_set": 2,
        "sides_changed": 0,
        "Action_FB_init_top": "Forehand",
        "Action_wl_init_top": "Winner",
        "Action_FB_init_bottom": "Forehand",
        "Action_wl_init_bottom": "Mistake",
        "shot": "Placement",
        "current_rally_top_init_score": 1,
        "current_rally_bottom_init_score": 0,
        "current_set_top_init_score": 15,
        "current_set_bottom_init_score": 19,
        "location_contact_shuttle": [
            274,
            1454,
            5
        ],
        "location_end_shuttle": [
            237,
            375,
            0
        ],
        "location_Init_start_top": [
            [
                370,
                1337
            ],
            [
                337,
                1414
            ]
        ],
        "location_Init_start_bottom": -1,
        "location_Init_end_top": [
            [
                370,
                1343
            ],
            [
                338,
                1416
            ]
        ],
        "location_Init_end_bottom": -1
    },
    "68": {
        "current_set": 2,
        "sides_changed": 0,
        "Action_FB_init_top": "Forehand",
        "Action_wl_init_top": "Winner",
        "shot": "Placement",
        "current_rally_top_init_score": 1,
        "current_rally_bottom_init_score": 0,
        "current_set_top_init_score": 16,
        "current_set_bottom_init_score": 19,
        "location_contact_shuttle": [
            501,
            1444,
            5
        ],
        "location_end_shuttle": [
            297,
            432,
            0
        ],
        "location_Init_start_top": -1,
        "location_Init_start_bottom": -1,
        "location_Init_end_top": -1,
        "location_Init_end_bottom": -1
    },
    "69": {
        "current_set": 2,
        "sides_changed": 0,
        "Action_FB_init_top": "Forehand",
        "Action_wl_init_top": "Mistake",
        "shot": "Placement",
        "current_rally_top_init_score": 0,
        "current_rally_bottom_init_score": 1,
        "current_set_top_init_score": 16,
        "current_set_bottom_init_score": 20,
        "location_contact_shuttle": [
            612,
            1194,
            5
        ],
        "location_end_shuttle": [
            264,
            176,
            0
        ],
        "location_Init_start_top": [
            [
                382,
                1139
            ],
            [
                492,
                1107
            ]
        ],
        "location_Init_start_bottom": [
            [
                620,
                209
            ],
            [
                524,
                222
            ]
        ],
        "location_Init_end_top": [
            [
                195,
                1293
            ],
            [
                325,
                1052
            ]
        ],
        "location_Init_end_bottom": [
            [
                448,
                315
            ],
            [
                362,
                247
            ]
        ]
    },
    "70": {
        "current_set": 2,
        "sides_changed": 0,
        "Action_FB_init_top": "Forehand",
        "Action_wl_init_top": "Winner",
        "Action_FB_init_bottom": "Backhand",
        "Action_wl_init_bottom": "Mistake",
        "shot": "Placement",
        "current_rally_top_init_score": 1,
        "current_rally_bottom_init_score": 0,
        "current_set_top_init_score": 17,
        "current_set_bottom_init_score": 20,
        "location_contact_shuttle": [
            620,
            1160,
            5
        ],
        "location_end_shuttle": [
            649,
            738,
            0
        ],
        "location_Init_start_top": -1,
        "location_Init_start_bottom": -1,
        "location_Init_end_top": -1,
        "location_Init_end_bottom": -1
    },
    "71": {
        "current_set": 2,
        "sides_changed": 0,
        "Action_FB_init_top": "Forehand",
        "Action_wl_init_top": "Winner",
        "Action_FB_init_bottom": "Backhand",
        "Action_wl_init_bottom": "Mistake",
        "shot": "Placement",
        "current_rally_top_init_score": 1,
        "current_rally_bottom_init_score": 0,
        "current_set_top_init_score": 18,
        "current_set_bottom_init_score": 20,
        "location_contact_shuttle": [
            510,
            1354,
            5
        ],
        "location_end_shuttle": [
            731,
            520,
            0
        ],
        "location_Init_start_top": -1,
        "location_Init_start_bottom": -1,
        "location_Init_end_top": -1,
        "location_Init_end_bottom": -1
    },
    "72": {
        "current_set": 2,
        "sides_changed": 0,
        "Action_FB_init_bottom": "Forehand",
        "Action_wl_init_bottom": "Winner",
        "shot": "Smash",
        "current_rally_top_init_score": 0,
        "current_rally_bottom_init_score": 1,
        "current_set_top_init_score": 18,
        "current_set_bottom_init_score": 21,
        "location_contact_shuttle": [
            635,
            466,
            5
        ],
        "location_end_shuttle": [
            220,
            1365,
            0
        ],
        "location_Init_start_top": -1,
        "location_Init_start_bottom": -1,
        "location_Init_end_top": -1,
        "location_Init_end_bottom": -1
    },
    "73": {
        "current_set": 2,
        "sides_changed": 0,
        "Action_FB_init_bottom": "Forehand",
        "Action_wl_init_bottom": "Mistake",
        "shot": "Placement",
        "current_rally_top_init_score": 1,
        "current_rally_bottom_init_score": 0,
        "current_set_top_init_score": 19,
        "current_set_bottom_init_score": 21,
        "location_contact_shuttle": [
            273,
            772,
            5
        ],
        "location_end_shuttle": [
            179,
            1467,
            0
        ],
        "location_Init_start_top": -1,
        "location_Init_start_bottom": -1,
        "location_Init_end_top": -1,
        "location_Init_end_bottom": -1
    },
    "74": {
        "current_set": 2,
        "sides_changed": 0,
        "Action_FB_init_top": "Backhand",
        "Action_wl_init_top": "Mistake",
        "Action_FB_init_bottom": "Backhand",
        "Action_wl_init_bottom": "Winner",
        "shot": "Placement",
        "current_rally_top_init_score": 0,
        "current_rally_bottom_init_score": 1,
        "current_set_top_init_score": 19,
        "current_set_bottom_init_score": 22,
        "location_contact_shuttle": [
            639,
            812,
            5
        ],
        "location_end_shuttle": [
            314,
            1183,
            0
        ],
        "location_Init_start_top": [
            [
                387,
                1263
            ],
            [
                415,
                1162
            ]
        ],
        "location_Init_start_bottom": [
            [
                101,
                507
            ],
            [
                143,
                420
            ]
        ],
        "location_Init_end_top": [
            [
                322,
                1204
            ],
            [
                362,
                1174
            ]
        ],
        "location_Init_end_bottom": [
            [
                124,
                397
            ],
            [
                112,
                409
            ]
        ]
    },
    "75": {
        "current_set": 2,
        "sides_changed": 0,
        "Action_FB_init_top": "Backhand",
        "Action_wl_init_top": "Mistake",
        "shot": "Placement",
        "current_rally_top_init_score": 0,
        "current_rally_bottom_init_score": 1,
        "current_set_top_init_score": 19,
        "current_set_bottom_init_score": 23,
        "location_contact_shuttle": [
            247,
            1396,
            5
        ],
        "location_end_shuttle": [
            134,
            580,
            0
        ],
        "location_Init_start_top": [
            [
                370,
                1155
            ],
            [
                385,
                1198
            ]
        ],
        "location_Init_start_bottom": [
            [
                530,
                260
            ],
            [
                518,
                247
            ]
        ],
        "location_Init_end_top": [
            [
                380,
                1113
            ],
            [
                436,
                1114
            ]
        ],
        "location_Init_end_bottom": [
            [
                557,
                129
            ],
            [
                558,
                115
            ]
        ]
    },
    "76": {
        "current_set": 2,
        "sides_changed": 0,
        "Action_FB_init_top": "Forehand",
        "Action_wl_init_top": "Mistake",
        "shot": "Placement",
        "current_rally_top_init_score": 0,
        "current_rally_bottom_init_score": 1,
        "current_set_top_init_score": 19,
        "current_set_bottom_init_score": 24,
        "location_contact_shuttle": [
            672,
            1194,
            5
        ],
        "location_end_shuttle": [
            290,
            303,
            0
        ],
        "location_Init_start_top": [
            [
                641,
                1419
            ],
            [
                668,
                1296
            ]
        ],
        "location_Init_start_bottom": -1,
        "location_Init_end_top": [
            [
                580,
                1247
            ],
            [
                635,
                1248
            ]
        ],
        "location_Init_end_bottom": -1
    },
    "77": {
        "current_set": 2,
        "sides_changed": 0,
        "Action_FB_init_bottom": "Backhand",
        "Action_wl_init_bottom": "Mistake",
        "shot": "Net Shot",
        "current_rally_top_init_score": 1,
        "current_rally_bottom_init_score": 0,
        "current_set_top_init_score": 20,
        "current_set_bottom_init_score": 24,
        "location_contact_shuttle": [
            728,
            611,
            5
        ],
        "location_end_shuttle": [
            773,
            410,
            0
        ],
        "location_Init_start_top": [
            [
                331,
                1017
            ],
            [
                353,
                996
            ]
        ],
        "location_Init_start_bottom": [
            [
                431,
                363
            ],
            [
                448,
                315
            ]
        ],
        "location_Init_end_top": [
            [
                354,
                1155
            ],
            [
                474,
                1149
            ]
        ],
        "location_Init_end_bottom": [
            [
                502,
                156
            ],
            [
                443,
                196
            ]
        ]
    },
    "78": {
        "current_set": 2,
        "sides_changed": 0,
        "Action_FB_init_top": "Backhand",
        "Action_wl_init_top": "Mistake",
        "shot": "Placement",
        "current_rally_top_init_score": 0,
        "current_rally_bottom_init_score": 1,
        "current_set_top_init_score": 20,
        "current_set_bottom_init_score": 25,
        "location_contact_shuttle": [
            278,
            1148,
            5
        ],
        "location_end_shuttle": [
            762,
            792,
            0
        ],
        "location_Init_start_top": [
            [
                423,
                1193
            ],
            [
                493,
                1252
            ]
        ],
        "location_Init_start_bottom": [
            [
                395,
                327
            ],
            [
                379,
                339
            ]
        ],
        "location_Init_end_top": [
            [
                542,
                1333
            ],
            [
                564,
                1370
            ]
        ],
        "location_Init_end_bottom": [
            [
                444,
                398
            ],
            [
                404,
                375
            ]
        ]
    },
    "79": {
        "current_set": 2,
        "sides_changed": 0,
        "Action_FB_init_top": "Backhand",
        "Action_wl_init_top": "Mistake",
        "shot": "Placement",
        "current_rally_top_init_score": 0,
        "current_rally_bottom_init_score": 1,
        "current_set_top_init_score": 20,
        "current_set_bottom_init_score": 26,
        "location_contact_shuttle": [
            255,
            1204,
            5
        ],
        "location_end_shuttle": [
            290,
            291,
            0
        ],
        "location_Init_start_top": [
            [
                206,
                1293
            ],
            [
                370,
                1294
            ]
        ],
        "location_Init_start_bottom": [
            [
                138,
                554
            ],
            [
                160,
                518
            ]
        ],
        "location_Init_end_top": [
            [
                232,
                1268
            ],
            [
                370,
                1294
            ]
        ],
        "location_Init_end_bottom": [
            [
                150,
                508
            ],
            [
                145,
                508
            ]
        ]
    },
    "80": {
        "current_set": 2,
        "sides_changed": 0,
        "Action_FB_init_bottom": "Backhand",
        "Action_wl_init_bottom": "Winner",
        "shot": "Placement",
        "current_rally_top_init_score": 0,
        "current_rally_bottom_init_score": 1,
        "current_set_top_init_score": 20,
        "current_set_bottom_init_score": 27,
        "location_contact_shuttle": [
            626,
            829,
            5
        ],
        "location_end_shuttle": [
            354,
            1110,
            0
        ],
        "location_Init_start_top": [
            [
                331,
                1155
            ],
            [
                480,
                1193
            ]
        ],
        "location_Init_start_bottom": [
            [
                579,
                410
            ],
            [
                477,
                273
            ]
        ],
        "location_Init_end_top": [
            [
                280,
                1204
            ],
            [
                259,
                1198
            ]
        ],
        "location_Init_end_bottom": [
            [
                402,
                432
            ],
            [
                397,
                421
            ]
        ]
    }
}